nice/__init__.py
nice/girl/__init__.py
nice/girl/message.py
Lwenxuan-0.2.dist-info/METADATA
Lwenxuan-0.2.dist-info/WHEEL
Lwenxuan-0.2.dist-info/top_level.txt
Lwenxuan-0.2.dist-info/RECORD
