Metadata-Version: 2.1
Name: Lwenxuan
Version: 0.2
Summary: 沈嘉怡，叶宇倩
Author: sjy,yyq
License: UNKNOWN
Platform: UNKNOWN
